ripiu/cmsplugin_rototalc/__init__.py
ripiu/cmsplugin_rototalc/apps.py
ripiu/cmsplugin_rototalc/cms_plugins.py
ripiu/cmsplugin_rototalc/models.py
ripiu/cmsplugin_rototalc/locale/it/LC_MESSAGES/django.mo
ripiu/cmsplugin_rototalc/locale/it/LC_MESSAGES/django.po
ripiu/cmsplugin_rototalc/migrations/0001_initial.py
ripiu/cmsplugin_rototalc/migrations/0002_carouselplugin_initial_slide.py
ripiu/cmsplugin_rototalc/migrations/0003_auto_20171207_1512.py
ripiu/cmsplugin_rototalc/migrations/0004_carouselplugin_header_alignment.py
ripiu/cmsplugin_rototalc/migrations/0005_auto_20180222_1602.py
ripiu/cmsplugin_rototalc/migrations/__init__.py
ripiu/cmsplugin_rototalc/migrations/__pycache__/0001_initial.cpython-36.pyc
ripiu/cmsplugin_rototalc/migrations/__pycache__/0002_carouselplugin_initial_slide.cpython-36.pyc
ripiu/cmsplugin_rototalc/migrations/__pycache__/0003_auto_20171207_1512.cpython-36.pyc
ripiu/cmsplugin_rototalc/migrations/__pycache__/0004_carouselplugin_header_alignment.cpython-36.pyc
ripiu/cmsplugin_rototalc/migrations/__pycache__/0005_auto_20180222_1602.cpython-36.pyc
ripiu/cmsplugin_rototalc/migrations/__pycache__/__init__.cpython-36.pyc
ripiu/cmsplugin_rototalc/static/ripiu/cmsplugin_rototalc/css/carousel.css
ripiu/cmsplugin_rototalc/templates/ripiu/cmsplugin_rototalc/carousel.html
ripiu/cmsplugin_rototalc/templates/ripiu/cmsplugin_rototalc/slide.html
ripiu.cmsplugin_rototalc-0.3.1.dist-info/DESCRIPTION.rst
ripiu.cmsplugin_rototalc-0.3.1.dist-info/METADATA
ripiu.cmsplugin_rototalc-0.3.1.dist-info/RECORD
ripiu.cmsplugin_rototalc-0.3.1.dist-info/WHEEL
ripiu.cmsplugin_rototalc-0.3.1.dist-info/metadata.json
ripiu.cmsplugin_rototalc-0.3.1.dist-info/top_level.txt
