Metadata-Version: 2.0
Name: ripiu.cmsplugin-rototalc
Version: 0.3.1
Summary: A plugin for Django-CMS to display galleries, based on Slick carousel
Home-page: https://github.com/ripiu/cmsplugin_rototalc
Author: matteo vezzola
Author-email: matteo@studioripiu.it
License: BSD-new
Platform: UNKNOWN
Classifier: Development Status :: 3 - Alpha
Classifier: Framework :: Django
Classifier: Intended Audience :: Developers
Classifier: License :: OSI Approved :: BSD License
Classifier: Operating System :: OS Independent
Classifier: Programming Language :: Python
Classifier: Topic :: Internet :: WWW/HTTP :: Dynamic Content
Requires-Python: >=3.3
Requires-Dist: Django (>=1.8)
Requires-Dist: django-cms (>=3.1)
Requires-Dist: django-sekizai (>=0.4.2)
Requires-Dist: django-appconf
